[
  {
    "id": 1356,
    "anime_id": 1356,
    "title": "X&amp;Y",
    "original_title": "X&amp;Y",
    "description": "an Yue Chu retourne dans sa ville natale pour y vivre et travailler. Un jour, il entre dans la chambre secrète XY afin de participer à un escape-game et attise l'intérêt de la propriétaire : Xu Ai You. Quelques temps après, de mystérieux incidents se produisent autour de Yan Yue Chu, impliquant même ses amis.",
    "image": "https://cdn.statically.io/gh/Anime-Sama/IMG/img/contenu/x-and-y.jpg",
    "image_url": "https://cdn.statically.io/gh/Anime-Sama/IMG/img/contenu/x-and-y.jpg",
    "genres": [
      "Mystère",
      "Enquête",
      "Psychologique",
      "Donghua"
    ],
    "seasons": [
      {
        "season_number": 1,
        "name": "Saison 1",
        "episodes": [
          {
            "episode_number": 1,
            "title": "Episode 1",
            "description": "",
            "duration": 0,
            "languages": [
              "VOSTFR"
            ],
            "urls": {
              "VOSTFR": [
                "https://sendvid.com/embed/s0p3uix9",
                "https://video.sibnet.ru/shell.php?videoid=5103113",
                "https://www.myvi.tv/embed/rj9oagj1h6or7gkfj7e6rgi6dh"
              ]
            }
          },
          {
            "episode_number": 2,
            "title": "Episode 2",
            "description": "",
            "duration": 0,
            "languages": [
              "VOSTFR"
            ],
            "urls": {
              "VOSTFR": [
                "https://sendvid.com/embed/adqw4zjd",
                "https://video.sibnet.ru/shell.php?videoid=5110295",
                "https://www.myvi.tv/embed/cfhpokkn9muwiqbuayb37bpbia"
              ]
            }
          },
          {
            "episode_number": 3,
            "title": "Episode 3",
            "description": "",
            "duration": 0,
            "languages": [
              "VOSTFR"
            ],
            "urls": {
              "VOSTFR": [
                "https://sendvid.com/embed/hfdqjome",
                "https://video.sibnet.ru/shell.php?videoid=5110298",
                "https://www.myvi.tv/embed/7du4mx73m81w3q9mi3ah4hghyr"
              ]
            }
          },
          {
            "episode_number": 4,
            "title": "Episode 4",
            "description": "",
            "duration": 0,
            "languages": [
              "VOSTFR"
            ],
            "urls": {
              "VOSTFR": [
                "https://sendvid.com/embed/b4oxbaqf",
                "https://video.sibnet.ru/shell.php?videoid=5117836",
                "https://www.myvi.tv/embed/o4ckgx5bi8cwf8epxwx4fmf89c"
              ]
            }
          },
          {
            "episode_number": 5,
            "title": "Episode 5",
            "description": "",
            "duration": 0,
            "languages": [
              "VOSTFR"
            ],
            "urls": {
              "VOSTFR": [
                "https://sendvid.com/embed/rb1tgxzg",
                "https://video.sibnet.ru/shell.php?videoid=5127210",
                "https://www.myvi.tv/embed/z6suhp5kcaawjrxhnme8dp398h"
              ]
            }
          },
          {
            "episode_number": 6,
            "title": "Episode 6",
            "description": "",
            "duration": 0,
            "languages": [
              "VOSTFR"
            ],
            "urls": {
              "VOSTFR": [
                "https://sendvid.com/embed/9bir1mvk",
                "https://video.sibnet.ru/shell.php?videoid=5136492",
                "https://www.myvi.tv/embed/a361sk8ozxzwukznu3becmsxyr"
              ]
            }
          },
          {
            "episode_number": 7,
            "title": "Episode 7",
            "description": "",
            "duration": 0,
            "languages": [
              "VOSTFR"
            ],
            "urls": {
              "VOSTFR": [
                "https://sendvid.com/embed/c4f6u68j",
                "https://video.sibnet.ru/shell.php?videoid=5142898",
                "https://www.myvi.tv/embed/bfdmx36qnharjfchiffnkhy95a"
              ]
            }
          },
          {
            "episode_number": 8,
            "title": "Episode 8",
            "description": "",
            "duration": 0,
            "languages": [
              "VOSTFR"
            ],
            "urls": {
              "VOSTFR": [
                "https://sendvid.com/embed/slsov63l",
                "https://video.sibnet.ru/shell.php?videoid=5150709",
                "https://www.myvi.tv/embed/forkbnoit43ruptjunro6szgcc"
              ]
            }
          },
          {
            "episode_number": 9,
            "title": "Episode 9",
            "description": "",
            "duration": 0,
            "languages": [
              "VOSTFR"
            ],
            "urls": {
              "VOSTFR": [
                "https://sendvid.com/embed/kktsnyr8",
                "https://video.sibnet.ru/shell.php?videoid=5157632",
                "https://www.myvi.tv/embed/6gxu3g59dj4wmfbkm4k3idtxoa"
              ]
            }
          },
          {
            "episode_number": 10,
            "title": "Episode 10",
            "description": "",
            "duration": 0,
            "languages": [
              "VOSTFR"
            ],
            "urls": {
              "VOSTFR": [
                "https://sendvid.com/embed/1lq1691y",
                "https://video.sibnet.ru/shell.php?videoid=5164286",
                "https://www.myvi.tv/embed/6jw6tnk69k5rdp5d17p1wcwato"
              ]
            }
          },
          {
            "episode_number": 11,
            "title": "Episode 11",
            "description": "",
            "duration": 0,
            "languages": [
              "VOSTFR"
            ],
            "urls": {
              "VOSTFR": [
                "https://sendvid.com/embed/d8icasgd",
                "https://video.sibnet.ru/shell.php?videoid=5171264",
                "https://www.myvi.tv/embed/u5hnbszep6srfges1ot9177oyr"
              ]
            }
          },
          {
            "episode_number": 12,
            "title": "Episode 12",
            "description": "",
            "duration": 0,
            "languages": [
              "VOSTFR"
            ],
            "urls": {
              "VOSTFR": [
                "https://sendvid.com/embed/2rcihcrf",
                "https://video.sibnet.ru/shell.php?videoid=5179669",
                "https://www.myvi.tv/embed/iowienwehrsrzpc1w5opfo685o"
              ]
            }
          },
          {
            "episode_number": 13,
            "title": "Episode 13",
            "description": "",
            "duration": 0,
            "languages": [
              "VOSTFR"
            ],
            "urls": {
              "VOSTFR": [
                "https://sendvid.com/embed/40syk0uh",
                "https://video.sibnet.ru/shell.php?videoid=5182537",
                "https://www.myvi.tv/embed/drzp84c845br3dsey8pw1huezw"
              ]
            }
          },
          {
            "episode_number": 14,
            "title": "Episode 14",
            "description": "",
            "duration": 0,
            "languages": [
              "VOSTFR"
            ],
            "urls": {
              "VOSTFR": [
                "https://sendvid.com/embed/a9r6n7bl",
                "https://video.sibnet.ru/shell.php?videoid=5191709",
                "https://www.myvi.tv/embed/ik68zkiuaygr5e75n5bs18ikuy"
              ]
            }
          },
          {
            "episode_number": 15,
            "title": "Episode 15",
            "description": "",
            "duration": 0,
            "languages": [
              "VOSTFR"
            ],
            "urls": {
              "VOSTFR": [
                "https://sendvid.com/embed/n2biv01t",
                "https://video.sibnet.ru/shell.php?videoid=5196206",
                "https://www.myvi.tv/embed/9zz7anck77triysaaxhcbpaw8c"
              ]
            }
          },
          {
            "episode_number": 16,
            "title": "Episode 16",
            "description": "",
            "duration": 0,
            "languages": [
              "VOSTFR"
            ],
            "urls": {
              "VOSTFR": [
                "https://sendvid.com/embed/oonpa98v",
                "https://video.sibnet.ru/shell.php?videoid=5201514",
                "https://www.myvi.tv/embed/9nwzp34k3cjw984m43g4irymqh"
              ]
            }
          }
        ]
      }
    ],
    "featured": false,
    "year": "",
    "status": "Disponible",
    "rating": 7.5,
    "languages": [
      "VOSTFR"
    ],
    "seasons_fetched": true,
    "has_episodes": true
  },
  {
    "id": 1357,
    "anime_id": 1357,
    "title": "xxxHolic",
    "original_title": "xxxHolic",
    "description": "Kimihiro Watanuki, lycéen, a depuis toujours la capacité de voir les esprits. Constamment piétiné ou bousculé par des ectoplasmes, il souhaite se débarrasser de ce don gênant. Un jour qu'il était pourchassé par l'un d'eux, Kimihiro entre par mégarde dans une étrange maison, coincée entre deux immeubles. C'est dans cette demeure singulière qu'il rencontre Y?ko Ichihara, qui se révèle être en mesure de lui retirer ce don qu'il déteste tant. Mais chez Y?ko, tout a un prix. Kimihiro va devoir aider la mystérieuse voyante dans son 'commerce de vœux', jusqu'à ce que la somme de son travail atteigne une valeur équivalente à son vœu. À travers ce petit job, il rencontrera nombre de personnes, et d'esprits, qu'il verra évoluer selon la politique de vente un peu particulière de Y?ko.",
    "image": "https://cdn.statically.io/gh/Anime-Sama/IMG/img/contenu/xxxholic.jpg",
    "image_url": "https://cdn.statically.io/gh/Anime-Sama/IMG/img/contenu/xxxholic.jpg",
    "genres": [
      "Comédie",
      "Drame",
      "Horreur",
      "Épouvante",
      "Mystère",
      "Psychologique",
      "Slice of Life",
      "Surnaturel"
    ],
    "seasons": [
      {
        "season_number": 1,
        "name": "Saison 1",
        "episodes": [
          {
            "episode_number": 1,
            "title": "Episode 1",
            "description": "",
            "duration": 0,
            "languages": [
              "VOSTFR"
            ],
            "urls": {
              "VOSTFR": [
                "https://sendvid.com/embed/cb5kck3g",
                "https://video.sibnet.ru/shell.php?videoid=4755649",
                "https://www.myvi.tv/embed/s93sr3k6sw6wprwcn3jympbufh"
              ]
            }
          },
          {
            "episode_number": 2,
            "title": "Episode 2",
            "description": "",
            "duration": 0,
            "languages": [
              "VOSTFR"
            ],
            "urls": {
              "VOSTFR": [
                "https://sendvid.com/embed/vxvr1ics",
                "https://video.sibnet.ru/shell.php?videoid=5049364",
                "https://www.myvi.tv/embed/ogggk6zyhqywzkp9s6gwxh8ote"
              ]
            }
          },
          {
            "episode_number": 3,
            "title": "Episode 3",
            "description": "",
            "duration": 0,
            "languages": [
              "VOSTFR"
            ],
            "urls": {
              "VOSTFR": [
                "https://sendvid.com/embed/lqz7n2ys",
                "https://video.sibnet.ru/shell.php?videoid=4755651",
                "https://www.myvi.tv/embed/ntyuwpimpyrrdpr7ypdb1cw3re"
              ]
            }
          },
          {
            "episode_number": 4,
            "title": "Episode 4",
            "description": "",
            "duration": 0,
            "languages": [
              "VOSTFR"
            ],
            "urls": {
              "VOSTFR": [
                "https://sendvid.com/embed/vwg6w43l",
                "https://video.sibnet.ru/shell.php?videoid=4755652",
                "https://www.myvi.tv/embed/5xtkibrpfgbwjqpgog34s3t87a"
              ]
            }
          },
          {
            "episode_number": 5,
            "title": "Episode 5",
            "description": "",
            "duration": 0,
            "languages": [
              "VOSTFR"
            ],
            "urls": {
              "VOSTFR": [
                "https://sendvid.com/embed/mywn6sd7",
                "https://video.sibnet.ru/shell.php?videoid=4755653",
                "https://www.myvi.tv/embed/pbaizhpdyjyrzmu6zf3uqe4k8w"
              ]
            }
          },
          {
            "episode_number": 6,
            "title": "Episode 6",
            "description": "",
            "duration": 0,
            "languages": [
              "VOSTFR"
            ],
            "urls": {
              "VOSTFR": [
                "https://sendvid.com/embed/n2jh67l8",
                "https://video.sibnet.ru/shell.php?videoid=4755654",
                "https://www.myvi.tv/embed/3jkmkprgwukrdcj4odgdbunk7c"
              ]
            }
          },
          {
            "episode_number": 7,
            "title": "Episode 7",
            "description": "",
            "duration": 0,
            "languages": [
              "VOSTFR"
            ],
            "urls": {
              "VOSTFR": [
                "https://sendvid.com/embed/7b4h5llr",
                "https://video.sibnet.ru/shell.php?videoid=4755655",
                "https://www.myvi.tv/embed/ohqcpb1pamyrimigj7kwxqn4ac"
              ]
            }
          },
          {
            "episode_number": 8,
            "title": "Episode 8",
            "description": "",
            "duration": 0,
            "languages": [
              "VOSTFR"
            ],
            "urls": {
              "VOSTFR": [
                "https://sendvid.com/embed/79ipiqi2",
                "https://video.sibnet.ru/shell.php?videoid=4755658",
                "https://www.myvi.tv/embed/9z97iqtx794rir48g8ibog4s1y"
              ]
            }
          },
          {
            "episode_number": 9,
            "title": "Episode 9",
            "description": "",
            "duration": 0,
            "languages": [
              "VOSTFR"
            ],
            "urls": {
              "VOSTFR": [
                "https://sendvid.com/embed/zryt4vf2",
                "https://video.sibnet.ru/shell.php?videoid=4755659",
                "https://www.myvi.tv/embed/515obbkr9b4rmj4awc6iemebbw"
              ]
            }
          },
          {
            "episode_number": 10,
            "title": "Episode 10",
            "description": "",
            "duration": 0,
            "languages": [
              "VOSTFR"
            ],
            "urls": {
              "VOSTFR": [
                "https://sendvid.com/embed/m86rlz5r",
                "https://video.sibnet.ru/shell.php?videoid=4755660",
                "https://www.myvi.tv/embed/7qn3io9iiscrdxfjqpddjerwbc"
              ]
            }
          },
          {
            "episode_number": 11,
            "title": "Episode 11",
            "description": "",
            "duration": 0,
            "languages": [
              "VOSTFR"
            ],
            "urls": {
              "VOSTFR": [
                "https://sendvid.com/embed/z7cbviov",
                "https://video.sibnet.ru/shell.php?videoid=4755661",
                "https://www.myvi.tv/embed/63hp3zhjpfawjq3g3k4em5tjyc"
              ]
            }
          },
          {
            "episode_number": 12,
            "title": "Episode 12",
            "description": "",
            "duration": 0,
            "languages": [
              "VOSTFR"
            ],
            "urls": {
              "VOSTFR": [
                "https://sendvid.com/embed/itd6oxzb",
                "https://video.sibnet.ru/shell.php?videoid=4755662",
                "https://www.myvi.tv/embed/14ijknuqeodrtg3s15he1hdoge"
              ]
            }
          },
          {
            "episode_number": 13,
            "title": "Episode 13",
            "description": "",
            "duration": 0,
            "languages": [
              "VOSTFR"
            ],
            "urls": {
              "VOSTFR": [
                "https://sendvid.com/embed/hjo5s82b",
                "https://video.sibnet.ru/shell.php?videoid=4755663",
                "https://www.myvi.tv/embed/kuf5te53nn8rfccfnxp63o5puw"
              ]
            }
          },
          {
            "episode_number": 14,
            "title": "Episode 14",
            "description": "",
            "duration": 0,
            "languages": [
              "VOSTFR"
            ],
            "urls": {
              "VOSTFR": [
                "https://sendvid.com/embed/tbo0x0zl",
                "https://video.sibnet.ru/shell.php?videoid=4755665",
                "https://www.myvi.tv/embed/8w8kuaawsh8r9jgqz4wjphmmoy"
              ]
            }
          },
          {
            "episode_number": 15,
            "title": "Episode 15",
            "description": "",
            "duration": 0,
            "languages": [
              "VOSTFR"
            ],
            "urls": {
              "VOSTFR": [
                "https://sendvid.com/embed/lfbrqd7c",
                "https://video.sibnet.ru/shell.php?videoid=4755666",
                "https://www.myvi.tv/embed/qrm5qm5qozmwtgaf7frujer86r"
              ]
            }
          },
          {
            "episode_number": 16,
            "title": "Episode 16",
            "description": "",
            "duration": 0,
            "languages": [
              "VOSTFR"
            ],
            "urls": {
              "VOSTFR": [
                "https://sendvid.com/embed/u7d2ux7u",
                "https://video.sibnet.ru/shell.php?videoid=4755667",
                "https://www.myvi.tv/embed/ehjg7juphtyr9gow48toinq35y"
              ]
            }
          },
          {
            "episode_number": 17,
            "title": "Episode 17",
            "description": "",
            "duration": 0,
            "languages": [
              "VOSTFR"
            ],
            "urls": {
              "VOSTFR": [
                "https://sendvid.com/embed/daomnuqt",
                "https://video.sibnet.ru/shell.php?videoid=4755668",
                "https://www.myvi.tv/embed/qfi9ozgcwttwd81sjb746myy8c"
              ]
            }
          },
          {
            "episode_number": 18,
            "title": "Episode 18",
            "description": "",
            "duration": 0,
            "languages": [
              "VOSTFR"
            ],
            "urls": {
              "VOSTFR": [
                "https://sendvid.com/embed/7kbnw0ba",
                "https://video.sibnet.ru/shell.php?videoid=4755669",
                "https://www.myvi.tv/embed/8375xxj5ch1r9rrgdh5dywnffc"
              ]
            }
          },
          {
            "episode_number": 19,
            "title": "Episode 19",
            "description": "",
            "duration": 0,
            "languages": [
              "VOSTFR"
            ],
            "urls": {
              "VOSTFR": [
                "https://sendvid.com/embed/og5s5v2g",
                "https://video.sibnet.ru/shell.php?videoid=4755670",
                "https://www.myvi.tv/embed/yq4xgtsm1fzrdfpxt7867xffae"
              ]
            }
          },
          {
            "episode_number": 20,
            "title": "Episode 20",
            "description": "",
            "duration": 0,
            "languages": [
              "VOSTFR"
            ],
            "urls": {
              "VOSTFR": [
                "https://sendvid.com/embed/zeu6izj1",
                "https://video.sibnet.ru/shell.php?videoid=4755671",
                "https://www.myvi.tv/embed/xu53dah5nwfrxppki8i4jdrycw"
              ]
            }
          },
          {
            "episode_number": 21,
            "title": "Episode 21",
            "description": "",
            "duration": 0,
            "languages": [
              "VOSTFR"
            ],
            "urls": {
              "VOSTFR": [
                "https://sendvid.com/embed/q7cbhm6b",
                "https://video.sibnet.ru/shell.php?videoid=4755672",
                "https://www.myvi.tv/embed/bwsi7fjzpoorjptf8f14k5dz7c"
              ]
            }
          },
          {
            "episode_number": 22,
            "title": "Episode 22",
            "description": "",
            "duration": 0,
            "languages": [
              "VOSTFR"
            ],
            "urls": {
              "VOSTFR": [
                "https://sendvid.com/embed/zwy4su5j",
                "https://video.sibnet.ru/shell.php?videoid=4755673",
                "https://www.myvi.tv/embed/5ik4yb15boywde1zk8144kc6bc"
              ]
            }
          },
          {
            "episode_number": 23,
            "title": "Episode 23",
            "description": "",
            "duration": 0,
            "languages": [
              "VOSTFR"
            ],
            "urls": {
              "VOSTFR": [
                "https://sendvid.com/embed/7lkypmcd",
                "https://video.sibnet.ru/shell.php?videoid=4755675",
                "https://www.myvi.tv/embed/en5zpngmh1hwdgxoecxbf9zdzc"
              ]
            }
          },
          {
            "episode_number": 24,
            "title": "Episode 24",
            "description": "",
            "duration": 0,
            "languages": [
              "VOSTFR"
            ],
            "urls": {
              "VOSTFR": [
                "https://sendvid.com/embed/3dsf77gh\t",
                "https://video.sibnet.ru/shell.php?videoid=4755677",
                "https://www.myvi.tv/embed/3u6c31ua5jzrzrd6x96qcxa5rc"
              ]
            }
          }
        ]
      },
      {
        "season_number": 2,
        "name": "Saison 2",
        "episodes": [
          {
            "episode_number": 1,
            "title": "Episode 1",
            "description": "",
            "duration": 0,
            "languages": [
              "VOSTFR"
            ],
            "urls": {
              "VOSTFR": [
                "https://sendvid.com/embed/7kv9yq8d",
                "https://video.sibnet.ru/shell.php?videoid=4755696",
                "https://www.myvi.tv/embed/cuo7pp1bk8yrtn6r7zqyt9orzc"
              ]
            }
          },
          {
            "episode_number": 2,
            "title": "Episode 2",
            "description": "",
            "duration": 0,
            "languages": [
              "VOSTFR"
            ],
            "urls": {
              "VOSTFR": [
                "https://sendvid.com/embed/cbtwvjzs",
                "https://video.sibnet.ru/shell.php?videoid=4755697",
                "https://www.myvi.tv/embed/3qphrgpjix1wfcq16qpbettbwc"
              ]
            }
          },
          {
            "episode_number": 3,
            "title": "Episode 3",
            "description": "",
            "duration": 0,
            "languages": [
              "VOSTFR"
            ],
            "urls": {
              "VOSTFR": [
                "https://sendvid.com/embed/upw0w9lg",
                "https://video.sibnet.ru/shell.php?videoid=4755698",
                "https://www.myvi.tv/embed/a8yrf3b7pi7wmyjgtk8e6zdbta"
              ]
            }
          },
          {
            "episode_number": 4,
            "title": "Episode 4",
            "description": "",
            "duration": 0,
            "languages": [
              "VOSTFR"
            ],
            "urls": {
              "VOSTFR": [
                "https://sendvid.com/embed/tzavyo3p",
                "https://video.sibnet.ru/shell.php?videoid=4755700",
                "https://www.myvi.tv/embed/eqenk1ykocgrpr4r1k7ioyqdqy"
              ]
            }
          },
          {
            "episode_number": 5,
            "title": "Episode 5",
            "description": "",
            "duration": 0,
            "languages": [
              "VOSTFR"
            ],
            "urls": {
              "VOSTFR": [
                "https://sendvid.com/embed/t6kbcr7n",
                "https://video.sibnet.ru/shell.php?videoid=4755703",
                "https://www.myvi.tv/embed/gyteubtocwqwxm93r5k8nt6oke"
              ]
            }
          },
          {
            "episode_number": 6,
            "title": "Episode 6",
            "description": "",
            "duration": 0,
            "languages": [
              "VOSTFR"
            ],
            "urls": {
              "VOSTFR": [
                "https://sendvid.com/embed/9lr7yqf0",
                "https://video.sibnet.ru/shell.php?videoid=4755704",
                "https://www.myvi.tv/embed/nnq4iu47duqw5nop3ccfkw58tr"
              ]
            }
          },
          {
            "episode_number": 7,
            "title": "Episode 7",
            "description": "",
            "duration": 0,
            "languages": [
              "VOSTFR"
            ],
            "urls": {
              "VOSTFR": [
                "https://sendvid.com/embed/2hrqm7or",
                "https://video.sibnet.ru/shell.php?videoid=4755705",
                "https://www.myvi.tv/embed/guwq9rxicwwr7kx9ikjz3xzh8y"
              ]
            }
          },
          {
            "episode_number": 8,
            "title": "Episode 8",
            "description": "",
            "duration": 0,
            "languages": [
              "VOSTFR"
            ],
            "urls": {
              "VOSTFR": [
                "https://sendvid.com/embed/tyjlmdt3",
                "https://video.sibnet.ru/shell.php?videoid=4755707",
                "https://www.myvi.tv/embed/sub7zfwzkn5wtnr7e3c8an9abo"
              ]
            }
          },
          {
            "episode_number": 9,
            "title": "Episode 9",
            "description": "",
            "duration": 0,
            "languages": [
              "VOSTFR"
            ],
            "urls": {
              "VOSTFR": [
                "https://sendvid.com/embed/6h1zj3d1",
                "https://video.sibnet.ru/shell.php?videoid=4755709",
                "https://www.myvi.tv/embed/su3knrrg6zprzn4s6cmozig78a"
              ]
            }
          },
          {
            "episode_number": 10,
            "title": "Episode 10",
            "description": "",
            "duration": 0,
            "languages": [
              "VOSTFR"
            ],
            "urls": {
              "VOSTFR": [
                "https://sendvid.com/embed/ez45t0co",
                "https://video.sibnet.ru/shell.php?videoid=4755715",
                "https://www.myvi.tv/embed/7fe4touj9hpw8fqwesyyqf84sy"
              ]
            }
          },
          {
            "episode_number": 11,
            "title": "Episode 11",
            "description": "",
            "duration": 0,
            "languages": [
              "VOSTFR"
            ],
            "urls": {
              "VOSTFR": [
                "https://sendvid.com/embed/k8lxbaw8",
                "https://video.sibnet.ru/shell.php?videoid=4755716",
                "https://www.myvi.tv/embed/daqj7nu59d9rid6bxghqdw7fye"
              ]
            }
          },
          {
            "episode_number": 12,
            "title": "Episode 12",
            "description": "",
            "duration": 0,
            "languages": [
              "VOSTFR"
            ],
            "urls": {
              "VOSTFR": [
                "https://sendvid.com/embed/fs9qqf9m",
                "https://video.sibnet.ru/shell.php?videoid=4755718",
                "https://www.myvi.tv/embed/pr9oomnu35yrbrmwk5pbi9r1zy"
              ]
            }
          },
          {
            "episode_number": 13,
            "title": "Episode 13",
            "description": "",
            "duration": 0,
            "languages": [
              "VOSTFR"
            ],
            "urls": {
              "VOSTFR": [
                "https://sendvid.com/embed/fn0o9x9x\t",
                "https://video.sibnet.ru/shell.php?videoid=4755719",
                "https://www.myvi.tv/embed/cnrwjkfqtcxwjmtezk949jy8sh"
              ]
            }
          }
        ]
      },
      {
        "season_number": 99,
        "name": "Film",
        "episodes": [
          {
            "episode_number": 1,
            "title": "Episode 1",
            "description": "",
            "duration": 0,
            "languages": [
              "VOSTFR"
            ],
            "urls": {
              "VOSTFR": [
                "https://video.sibnet.ru/shell.php?videoid=4755755\t",
                "https://sendvid.com/embed/x0x5wqse",
                "https://www.myvi.tv/embed/weapwd5w4tywpgxuurjyd171ny"
              ]
            }
          }
        ]
      },
      {
        "season_number": 5,
        "name": "OAV",
        "episodes": [
          {
            "episode_number": 1,
            "title": "Episode 1",
            "description": "",
            "duration": 0,
            "languages": [
              "VOSTFR"
            ],
            "urls": {
              "VOSTFR": [
                "https://sendvid.com/embed/sw27a22n",
                "https://video.sibnet.ru/shell.php?videoid=4755758",
                "https://www.myvi.tv/embed/4ti1oj9u7pzwpcat73m8n4g9dy"
              ]
            }
          },
          {
            "episode_number": 2,
            "title": "Episode 2",
            "description": "",
            "duration": 0,
            "languages": [
              "VOSTFR"
            ],
            "urls": {
              "VOSTFR": [
                "https://sendvid.com/embed/bhrka1dc",
                "https://video.sibnet.ru/shell.php?videoid=4755761",
                "https://www.myvi.tv/embed/489xopf8w6jwdr3wng7jxmjjqy"
              ]
            }
          },
          {
            "episode_number": 3,
            "title": "Episode 3",
            "description": "",
            "duration": 0,
            "languages": [
              "VOSTFR"
            ],
            "urls": {
              "VOSTFR": [
                "https://sendvid.com/embed/2zp5aiek",
                "https://video.sibnet.ru/shell.php?videoid=4755762",
                "https://www.myvi.tv/embed/rcarf75tniyw8b4hq9pkryn44c"
              ]
            }
          },
          {
            "episode_number": 4,
            "title": "Episode 4",
            "description": "",
            "duration": 0,
            "languages": [
              "VOSTFR"
            ],
            "urls": {
              "VOSTFR": [
                "https://sendvid.com/embed/xad5jn90\t",
                "https://video.sibnet.ru/shell.php?videoid=4755763",
                "https://www.myvi.tv/embed/ukjc6ra8wqkrpfxyxdfxqcy8zy"
              ]
            }
          }
        ]
      }
    ],
    "featured": false,
    "year": "",
    "status": "Disponible",
    "rating": 7.5,
    "languages": [
      "VOSTFR"
    ],
    "seasons_fetched": true,
    "has_episodes": true
  }
]